CHANGELOG.txt
LICENSE.txt
MANIFEST.in
README.md
setup.py
ymcntr/__init__.py
ymcntr.egg-info/PKG-INFO
ymcntr.egg-info/SOURCES.txt
ymcntr.egg-info/dependency_links.txt
ymcntr.egg-info/top_level.txt