Metadata-Version: 2.1
Name: ymcntr
Version: 0.0.1
Summary: Module of basic calculations
Home-page: https://github.com
Author: Yam
Author-email: ymgchbrtv0095@gmail.com
License: MIT
Keywords: calculator,math
Platform: UNKNOWN
Classifier: Development Status :: 5 - Production/Stable
Classifier: Intended Audience :: Education
Classifier: Intended Audience :: Financial and Insurance Industry
Classifier: Operating System :: OS Independent
Classifier: License :: OSI Approved :: MIT License
Classifier: Programming Language :: Python :: 3
